pygments_simtalk/__init__.py
pygments_simtalk/simtalk_lexer.py
pygments_simtalk-0.1.3.dist-info/LICENSE.MD
pygments_simtalk-0.1.3.dist-info/METADATA
pygments_simtalk-0.1.3.dist-info/WHEEL
pygments_simtalk-0.1.3.dist-info/entry_points.txt
pygments_simtalk-0.1.3.dist-info/RECORD
