Metadata-Version: 2.1
Name: pygments-simtalk
Version: 0.1.3
Summary: A Pygments lexer for the SimTalk programming language.
Home-page: https://github.com/sean-reed/pygments-simtalk/
License: MIT
Author: Sean Reed
Author-email: sean@sean-reed.com
Requires-Python: >=3.10,<4.0
Classifier: License :: OSI Approved :: MIT License
Classifier: Programming Language :: Python :: 3
Classifier: Programming Language :: Python :: 3.10
Classifier: Programming Language :: Python :: 3.11
Classifier: Programming Language :: Python :: 3.12
Requires-Dist: pygments (>=2.18.0,<3.0.0)
Project-URL: Repository, https://github.com/sean-reed/pygments-simtalk/
